monitor/__init__.py
monitor/__main__.py
monitor/app.py
monitor/capture.py
monitor/command.py
monitor/config.py
monitor/log.py
monitor/policy.py
monitor/server.py
monitor/video.py
work_monitor-0.1.4.dist-info/LICENSE
work_monitor-0.1.4.dist-info/METADATA
work_monitor-0.1.4.dist-info/WHEEL
work_monitor-0.1.4.dist-info/entry_points.txt
work_monitor-0.1.4.dist-info/top_level.txt
work_monitor-0.1.4.dist-info/RECORD
