Metadata-Version: 2.1
Name: work-monitor
Version: 0.1.4
Summary: monitor work environment by camera
Author-email: caibingcheng <jack_cbc@163.com>
Requires-Python: >=3.7
License-File: LICENSE
Requires-Dist: requests
Requires-Dist: opencv-python
